{
  "meta_version": 2,
  "build": {
    "date": "2026-06-21T09:56:55Z",
    "commit": "84a8012058a8d79997c2a7ee8215a97abeaf9f89",
    "branch": "nightly",
    "workflow_run_id": 27900731859
  },
  "toolchain": {
    "python": "3.12.13",
    "pyinstaller": "6.21.0",
    "builder_os": "ubuntu-latest"
  },
  "artifacts": [
    {
      "name": "RunUpdates_1.0.0.deb",
      "type": "deb",
      "os": "linux",
      "arch": "amd64",
      "size": 20300936,
      "sha256": "b04bf43cf09d909794ed490b7ca209cbf841f9ad403b51d270a965fd1ba263b0",
      "crc32": "a0fa620f"
    }
,
    {
      "name": "RunUpdates_1.0.0.tgz",
      "type": "tgz",
      "os": "linux",
      "arch": "amd64",
      "size": 20410759,
      "sha256": "c889aea9084dab5410ae3ab70078a533c89f69d2d40137d78ac8381ac9a5fcf0",
      "crc32": "d3e2ee63"
    }
,
    {
      "name": "RunUpdates_1.0.0.x86_64.rpm",
      "type": "rpm",
      "os": "linux",
      "arch": "x86_64",
      "size": 20425758,
      "sha256": "4a474abd930ef50c8bbcf80fea46a60f7c91c8272e08c67f3c7792418c3e5294",
      "crc32": "20e64d30"
    }
,
    {
      "name": "RunUpdates_1.0.0.zip",
      "type": "zip",
      "os": "windows",
      "arch": "x86_64",
      "size": 20412539,
      "sha256": "9486fba02cffa8e289b5fca9d317fbbf2e5bcba110e8d84dafcb807263ad7ad0",
      "crc32": "b84c9aaa"
    }
  ]
}
